myprogressbar/__init__.py
myprogressbar-0.0.1.dist-info/METADATA
myprogressbar-0.0.1.dist-info/WHEEL
myprogressbar-0.0.1.dist-info/top_level.txt
myprogressbar-0.0.1.dist-info/RECORD
