Metadata-Version: 2.1
Name: myprogressbar
Version: 0.0.1
Summary: Progress bar as a Service
Home-page: https://example.com/
Author: Kota Uenishi
Author-email: kuenishi@gmail.com
License: UNKNOWN
Platform: UNKNOWN
